{
  "country_code": "KAZ",
  "country_name": "Kazakhstan",
  "given_names_male": {
    "top": [
      "Vladimir",
      "Amir",
      "Oleg",
      "Alikhan",
      "Denis"
    ],
    "very_common": [
      "Aisultan",
      "Ruslan",
      "Nursultan",
      "Ivan",
      "Sultan",
      "Artem",
      "Ayan",
      "Igor",
      "Temirlan",
      "Maksim"
    ],
    "common": [
      "Arsen",
      "Roman",
      "Alan",
      "Anton",
      "Miras",
      "Viktor",
      "Islam",
      "Nikita",
      "Ramazan",
      "Pavel",
      "Nurali",
      "Vadim",
      "Daniyar",
      "Kirill",
      "Asylkhan",
      "Timur",
      "Arman",
      "Sergey",
      "Adilet",
      "Vlad",
      "Aldiyar",
      "Ilja",
      "Madi",
      "Azamat"
    ],
    "familiar": [
      "Erkebulan",
      "Sanzhar",
      "Alex",
      "Yerkhan",
      "Vladislav",
      "Marat",
      "Dias",
      "Rustam",
      "Ilyas",
      "Alexey",
      "Nurlan",
      "Andrey",
      "Alexandr",
      "Murat",
      "Dauren",
      "Erlan",
      "Maxim",
      "Boris",
      "Samat",
      "Petr",
      "Kanat",
      "Damir",
      "Dmitriy",
      "David",
      "Ali",
      "Alexander",
      "Dmitry",
      "Alisher",
      "Adil",
      "Askar",
      "Talgat",
      "Michael",
      "John",
      "Erbol",
      "Anuar",
      "Alibek"
    ],
    "uncommon": [
      "Yevgeniy",
      "Eldar",
      "Aslan",
      "Vitaliy",
      "Ryan",
      "Rinat",
      "Kairat",
      "Aidos",
      "Paul",
      "Martin",
      "Andy",
      "Adam",
      "Rustem",
      "Mikhail",
      "Andrew",
      "Yerlan",
      "Stas",
      "Robert",
      "Renat",
      "Peter",
      "Nikolay",
      "Mike",
      "Aidar",
      "Albert",
      "Rafael",
      "Aidyn",
      "Nurbol",
      "Aibek",
      "Raushan",
      "Omar",
      "Ramil",
      "Gleb",
      "Almat",
      "Yuriy",
      "Aleksey",
      "Zhalgas",
      "Mustafa",
      "Mark",
      "Anvar",
      "Didar",
      "Justin",
      "Berik",
      "Anar",
      "Ildar",
      "Evgeniy",
      "Dan",
      "Vitaly",
      "Saken",
      "Ilya",
      "Daniel",
      "Sergei",
      "Nazym",
      "Zhan",
      "Jason",
      "Abzal",
      "Chris",
      "Abay",
      "Dastan",
      "Olzhas",
      "Erik",
      "Nick",
      "Brian",
      "Vyacheslav",
      "Aziz",
      "Victor",
      "Tim",
      "Erkin",
      "Sam",
      "Mika",
      "Mehmet",
      "Jan",
      "James",
      "Jake",
      "Otabek",
      "Bill",
      "Thomas",
      "Tyler",
      "Matt",
      "Jack",
      "Alen",
      "Sean",
      "Vasiliy",
      "Mohammad",
      "Yerzhan",
      "Medet",
      "Valeriy",
      "Steve",
      "Amanzhol",
      "Dimash",
      "Malik",
      "Art",
      "Ben",
      "Eric",
      "Park",
      "Ibrahim",
      "Joseph",
      "Valter",
      "Max",
      "George",
      "Don",
      "Kevin",
      "Nate",
      "Galymzhan",
      "Dave",
      "Nik",
      "Morgan",
      "Will",
      "Sabit",
      "Maksut",
      "Ismail",
      "Rauan",
      "Beka",
      "Bob",
      "Nurdaulet",
      "Madiyar",
      "Taylor",
      "Rob",
      "Jose",
      "Gabit",
      "Richard",
      "Steven",
      "Frank",
      "Bek",
      "Lee",
      "Kris",
      "Stephen",
      "Hakan",
      "Kamran",
      "Jay",
      "Anthony",
      "Evgeny",
      "Joshua",
      "Charlie",
      "William",
      "Jon",
      "Greg",
      "Jim",
      "Matthew",
      "Rashid",
      "Oğuz",
      "Josh",
      "Bakhtiyar",
      "Nuri",
      "Jeff",
      "Jonathan",
      "German",
      "Ahmet",
      "Joe",
      "Kyle"
    ],
    "rare": [],
    "very_rare": []
  },
  "surnames": {
    "top": [
      "Kenes",
      "Omarov",
      "Sultanov",
      "Barat",
      "Akhmetov"
    ],
    "very_common": [
      "Umarov",
      "Belgibaev",
      "Kemelov",
      "Bolatbek",
      "Ivanov",
      "Kambarov",
      "Boyko",
      "Smagulov",
      "Aliev",
      "Ospanov"
    ],
    "common": [
      "Serikov",
      "Tsoy",
      "Suleymenov",
      "Karimov",
      "Ibragimov",
      "Bondarenko",
      "Eleusiz",
      "Kaliev",
      "Nigmashev",
      "Shevchenko",
      "Popov",
      "Muratov",
      "Romanyuk",
      "Asanov",
      "Ibraev",
      "Zhumabaev",
      "Ismailov",
      "Kovalenko",
      "Sarbalin",
      "Tulegenov",
      "Iskakov",
      "Musin",
      "Mamedov",
      "Abdullaev"
    ],
    "familiar": [
      "Musaev",
      "Nurdulla",
      "Amangeldi",
      "Kudarov",
      "Nauryzbaev",
      "Nurgaliev",
      "Bazarbaev",
      "Mukashev",
      "Isaev",
      "Zhumagaliev",
      "Amangeldy",
      "Bisenov",
      "Galiev",
      "Sadykov",
      "Sauytbay",
      "Sharipov",
      "Sarsenbaev",
      "Shaymerdenov",
      "Amangeldiev",
      "Mamirov",
      "Beshirov",
      "Amanzholov",
      "Serikbaev",
      "Askarov",
      "Mukanov",
      "Yusupov",
      "Ramazanov",
      "Chebotar",
      "Abuov",
      "Saparov",
      "Shnayder",
      "Aymushev",
      "Bekenov",
      "Parasyukov",
      "Kuanyshev",
      "Aubakirov"
    ],
    "uncommon": [
      "Rakhmetov",
      "Khan",
      "Zhaikbaev",
      "Zhumadilov",
      "Esimkhanov",
      "Syzdykov",
      "Kuznetsov",
      "Orazbaev",
      "Utegenov",
      "Kusainov",
      "Abdrakhmanov",
      "Gumarov",
      "Shmidt",
      "Nazarenko",
      "Kurbanov",
      "Levitskaya",
      "Tkachenko",
      "Abenov",
      "Rakhmanianov",
      "Lysenko",
      "Alpeisov",
      "Morozov",
      "Orlov",
      "Vasilyev",
      "Ordabaev",
      "Serikbay",
      "Mayer",
      "Maratov",
      "Zhanibekov",
      "Dauletov",
      "Orynbasar",
      "Kravchenko",
      "Erzhanov",
      "Derbisov",
      "Kadyrov",
      "Kasimov",
      "Bolatov",
      "Ergaliev",
      "Islamov",
      "Zhumabek",
      "Rudenko",
      "Zhusupov",
      "Amanov",
      "Usenov",
      "Musina",
      "Zhumabekov",
      "Zhumanov",
      "Tolegen",
      "Rakhimov",
      "Serik",
      "Abishev",
      "Kasenov",
      "Zhumakhan",
      "Mukazhan",
      "Zhardemov",
      "Novikov",
      "Kasymov",
      "Burankulov",
      "Khasanov",
      "Khayrulina",
      "Voyskovaya",
      "Abilov",
      "Kozlov",
      "Volkov",
      "Nazarov",
      "Zhenisov",
      "Tolegenov",
      "Melnikov",
      "Kuzmin",
      "Zhunusov",
      "Sabirov",
      "Nabiev",
      "Adilov",
      "Alibekov",
      "Ashimov",
      "Kadirov",
      "Makarov",
      "Sokolov",
      "Erzin",
      "Kasatkin",
      "Ilyasov",
      "Bizhanov",
      "Stepanov",
      "Bolat",
      "Aman",
      "Ergeshov",
      "Mametov",
      "Amirov",
      "Mikheev",
      "Egorov",
      "Tyan",
      "Muldagaliev",
      "Babaev",
      "Elemesov",
      "Smirnov",
      "Zhumagulov",
      "Miroshnichenko",
      "Kaldybaev",
      "Lesbek",
      "Ismagulov",
      "Kenesov",
      "Babenko",
      "Akhmedov",
      "Tursunov",
      "Samenov",
      "Gabdullin",
      "Eskaliev",
      "Kalashnikov",
      "Beysembaev",
      "Umbetov",
      "Skulkin",
      "Aimukhambet",
      "Abdraimov",
      "Nikitina",
      "Aytzhanov",
      "Mukhatov",
      "Ali",
      "Tolendi",
      "Nusipov",
      "Abdrazakov",
      "Kim",
      "Sakhipov",
      "Tulebaev",
      "Zhakupov",
      "Sarsenov",
      "Romanenko",
      "Valiev",
      "Kudaybergenov",
      "Gizatulina",
      "Khasenov",
      "Nikitin",
      "Isakov",
      "Shulgin",
      "Erdesbay",
      "Omirzak",
      "Mukhambetov",
      "Melnik",
      "Nurbaev",
      "Nurzhanov",
      "Eszhanov",
      "Klimenko",
      "Sultan",
      "Vagner",
      "Erken",
      "Mustafina",
      "Kayratov",
      "Sabitov",
      "Sergienko",
      "Khamitov",
      "Asan",
      "Belik",
      "Belyaev",
      "Ormanov",
      "Orazbekov",
      "Mukhamedzhanov",
      "Yakovlev",
      "Yurchenko",
      "Ahmetov",
      "Omar",
      "Amanbek",
      "Khegay",
      "Gorbunov",
      "Andreev",
      "Isabekov",
      "Kozhakhmetov",
      "Kolesnikov",
      "Litvinenko",
      "Aydarov",
      "Zholdas",
      "Usmanov",
      "Kirichenko",
      "Dmitrienko",
      "Zhaxylyk",
      "Kabiev",
      "Talgatov"
    ],
    "rare": [
      "Mukhtarov",
      "Badulin",
      "Imangaliev",
      "Sundetov",
      "Akhmetzhanov",
      "Amanbaev",
      "Kudashev",
      "Vasilev",
      "Bisengaliev",
      "Ermakov",
      "Kudaybergen",
      "Bashkaraev",
      "Petrenko",
      "Isabaev",
      "Baratov",
      "Nurgali",
      "Panchenko",
      "Savchenko",
      "Malikov",
      "Nasyrov",
      "Alimov",
      "Kulmagambetov",
      "Karzhaubaev",
      "Nurbay",
      "Akaev",
      "Kaziev",
      "Salibekov",
      "Beysenov",
      "Akzhigitov",
      "Kultasbekov",
      "Pavlov",
      "Nikolaev",
      "Batalov",
      "Sobchenko",
      "Zhaksylyk",
      "Baltabaev",
      "Amantaev",
      "Maxutov",
      "Pavlenko",
      "Turganbek",
      "Zakharov",
      "Dosanov",
      "Breyt",
      "Altaev",
      "Kabylbekov",
      "Shayakhmetov",
      "Nechaev",
      "Shin",
      "Bekmuratov",
      "Khamzina",
      "Sagimbaev",
      "Kogay",
      "Amangaliev",
      "Nurbekov",
      "Pakhomov",
      "Kuralov",
      "Mikhaylov",
      "Sattarov",
      "Esengaliev",
      "Alzhanov",
      "Karabaev",
      "Osmanov",
      "Kalmenov",
      "Alpysbaev",
      "Sidorenko",
      "Turzhanov",
      "Zhanalisov",
      "Kononenko",
      "Sapar",
      "Ermakhan",
      "Mustafin",
      "Kenzhebaev",
      "Dautov",
      "Baydullaev",
      "Bekzhanov",
      "Fomenko",
      "Sembek",
      "Dosov",
      "Kumarov",
      "Sultanbek",
      "Mustafaev",
      "Medvedev",
      "Malik",
      "Baktybaev",
      "Umirzakov",
      "Svinarchuk",
      "Imashev",
      "Yadryonkin",
      "Ermekov",
      "Fokin",
      "Talipov",
      "Sarkisyan",
      "Kuandyk",
      "Atabaev",
      "Zaytsev",
      "Vlasov",
      "Uskenbaev",
      "Gazizov",
      "Saken",
      "Alimzhanov",
      "Yugay",
      "Kamalov",
      "Bekbaev",
      "Dyusekov",
      "Belov",
      "Zakirov",
      "Abdramanov",
      "Baubekov",
      "Abdrahmanov",
      "Medet",
      "Sidorov",
      "Mansurov",
      "Shakirov",
      "Shevchuk",
      "Idrisov",
      "Zhanyarov",
      "Zuev",
      "Zhasuzak",
      "Mazhitov",
      "Filimonov",
      "Turarov",
      "Skiba",
      "Abiltaev",
      "Sydykov",
      "Onalbay",
      "Khamzin",
      "Kurgambaev",
      "Baetov",
      "Dzizenko",
      "Kramer",
      "Moldagaliev",
      "Adrisov",
      "Menshikov",
      "Torekhan",
      "Kovalev",
      "Sagyndykov",
      "Sergeev",
      "Tazhibek",
      "Nesterenko",
      "Anarbek",
      "Kanatov",
      "Abelbasov",
      "Ermekbaev",
      "Nepogodina",
      "Tomin",
      "Gabit",
      "Temnikov",
      "Asylbekov",
      "Zhubanov",
      "Atabay",
      "Kuanyshbai",
      "Sarsen",
      "Kuzmina",
      "Deyneko",
      "Zeynov",
      "Frolov",
      "Taldybay",
      "Miller",
      "Nagorny",
      "Murzagali",
      "Karibaev",
      "Fomina",
      "Manap",
      "Kolesnik",
      "Kuanov",
      "Ablaev",
      "Kulmanov",
      "Mironov",
      "Klimov",
      "Makhanbetov",
      "Kairatovna",
      "Kovalchuk",
      "Shymyrbaev",
      "Mambetov",
      "Turaliev",
      "Zhangylyshev",
      "Amantay",
      "Matzhanov",
      "Zhumanazarov",
      "Sandybaev",
      "Makhanov",
      "Tastemir",
      "Orazov",
      "Karabalin",
      "Gerasimov",
      "Rodionov",
      "Alimbaev",
      "Smailov",
      "Sorokin",
      "Daku",
      "Gapparov",
      "Madiev",
      "Goncharov",
      "Kyrykbaev",
      "Mikhaylenko",
      "Rakhmanov",
      "Solovev",
      "Boranbaev",
      "Abubakirov",
      "Akylbek",
      "Romanov",
      "Saduakas",
      "Smanov",
      "Saduakasov",
      "Akylbekov",
      "Litvinov",
      "Sherer",
      "Lebedev",
      "Zhorabekov",
      "Fedorov",
      "Borisov",
      "Alimbek",
      "Zhaxylykov",
      "Kaldybek",
      "Shvarts",
      "Urazbaev",
      "Vasilenko",
      "Ilina",
      "Fyodorov",
      "Shishkin",
      "Tayzhanov",
      "Plotnikov",
      "Zhanabaev",
      "Shalabaev",
      "Tanatarov",
      "Imanbaev",
      "Izbasarov",
      "Abdulaev",
      "Satybaldiev",
      "Lyan",
      "Nigmetov",
      "Suleymanov",
      "Levchenko",
      "Bakyt",
      "Aleksandrov",
      "Agafonov",
      "Niyazov",
      "Orynbaev",
      "Nurlanov",
      "Satybaldy",
      "Fisher",
      "Moldabekov",
      "Sadvakasov",
      "Ilesov",
      "Tarasenko",
      "Lukyanov",
      "Ikhsanov",
      "Turganbaev",
      "Myrzabek",
      "Turar",
      "Chernov",
      "Aldanov",
      "Fomin",
      "Akhmet",
      "Ustemirov",
      "Anuarbekov",
      "Kharchenko",
      "Shapovalov",
      "Kanaev",
      "Marchenko",
      "Ponomarenko",
      "Nurgozhaev",
      "Ernazarov",
      "Gimranov",
      "Farkhutdinov",
      "Maratovna",
      "Bondar",
      "Maksimov",
      "Yakupov",
      "Sakenov",
      "Kudaibergenov",
      "Bisenbaev",
      "Ryabov",
      "Eraliev",
      "Kuangaliev",
      "Ashirov",
      "Meldebekov",
      "Makhambetov",
      "Akbaev",
      "Arynov",
      "Kuzmenko",
      "Stanbekov",
      "Timoshenko",
      "Alimkhan",
      "Moldagazin",
      "Saparbaev",
      "Shynarov",
      "Suleimenov",
      "Tasboltaev",
      "Fominykh",
      "Bekzadaev",
      "Mendigaliev",
      "Stryapunin",
      "Khusainov",
      "Baysalov",
      "Murzagaliev",
      "Tsay",
      "Kasymbek",
      "Agarkina",
      "Saktaganov",
      "Batyrbekov",
      "Kulikov",
      "Karabalaev",
      "Kurmangaliev",
      "Tleubaev",
      "Makhmetov",
      "Grigoryev",
      "Didenko",
      "Samatov",
      "Kazakov",
      "Bekbolat",
      "Seitov",
      "Vinogradov",
      "Zhamalov",
      "Zhumakulov",
      "Akhanov",
      "Kenesbekov",
      "Moldashev",
      "Pakharenko",
      "Nugmanov",
      "Chzhan",
      "Tolybay",
      "Kuandykov",
      "Mentay",
      "Mambetkulov",
      "Aldabergenov",
      "Amal",
      "Kazbekov",
      "Momotov",
      "Tokarev",
      "Userbaev",
      "Amirekulov",
      "Isaykina",
      "Zholdasov",
      "Nurylla",
      "Izbasar",
      "Zharekov",
      "Azizov",
      "Tashekenov",
      "Kiselev",
      "Esenov",
      "Zhaksylykov",
      "Yuldashev",
      "Bektemirov",
      "Borisenko",
      "Tazhibaev",
      "Tursyn",
      "Matveev",
      "Rakhimzhanov",
      "Uzakbaev",
      "Nurkenov",
      "Makhmutov",
      "Kuralbaev",
      "Karpenko",
      "Tolkynov",
      "Myrzagaliev",
      "Dyachenko",
      "Antonov",
      "Moldakhmetov",
      "Tishininov",
      "Danilov",
      "Stepanenko",
      "Semenov",
      "Tlegenov",
      "Radchenko",
      "Bakirov",
      "Gabbasov",
      "Koshevets",
      "Son",
      "Tileubai",
      "Bigaliev",
      "Ishchanov",
      "Parkhomenko",
      "Dursunov",
      "Velichko",
      "Ibraimov",
      "Ovsyannikov",
      "Denisenko",
      "Kurmanbek",
      "Akimov",
      "Kerimbekov",
      "Khvan",
      "Duysenov",
      "Kurmanov",
      "Roziev",
      "Karazhanov",
      "Serikuly",
      "Bannikov",
      "Zinchenko",
      "Nurpeisov",
      "Zhukov",
      "Serikovna",
      "Muratovna",
      "Agadilov",
      "Lim",
      "Bayzhanov",
      "Tursynov",
      "Antropov",
      "Ermagambetov",
      "Bergaliev",
      "Gabdullina",
      "Zhakenov",
      "Yakovenko",
      "Kuanyshkali",
      "Utebaev",
      "Kabylov",
      "Kutzhan",
      "Tastanbekov",
      "Kasymbekov",
      "Auesov",
      "Kabdeshev",
      "Guseynov",
      "Abaev",
      "Talgatuly",
      "Moldabaev",
      "Nysanov",
      "Prikhodko",
      "Saparbekov",
      "Doroshenko",
      "Sagyndykuly",
      "Kochergin",
      "Zharas",
      "Kayratkyzy",
      "Sembaev",
      "Alekseev",
      "Ordabek",
      "Osipov",
      "Tazhenov",
      "Zhan",
      "Abdirov",
      "Scherbakov",
      "Temirkhan",
      "Utegaliev",
      "Korenkov",
      "Lopatin",
      "Anokhin",
      "Sansyzbaev",
      "Shaykenov",
      "Semyonov",
      "Esmagambetov",
      "Nurmagambet",
      "Tursingaliev",
      "Sekerov",
      "Bekzhigitov",
      "Kulbaev",
      "Surumbaev",
      "Karaev",
      "Nazarbaev"
    ],
    "very_rare": []
  },
  "tier_probs": {
    "given": {
      "top": 0.11,
      "very_common": 0.12,
      "common": 0.12,
      "familiar": 0.15,
      "uncommon": 0.5,
      "rare": 0.0,
      "very_rare": 0.0
    },
    "surname": {
      "top": 0.12999999999999998,
      "very_common": 0.16999999999999998,
      "common": 0.15999999999999998,
      "familiar": 0.18999999999999995,
      "uncommon": 0.13999999999999996,
      "rare": 0.20999999999999994,
      "very_rare": 0.0
    }
  },
  "middle_name_prob": 0.15,
  "compound_surname_prob": 0.05,
  "surname_connector": "-",
  "pool_id": "country_KAZ",
  "rarity_profile": "mixed"
}
