{
  "country_code": "UZB",
  "country_name": "Uzbekistan",
  "given_names_male": {
    "very_common": [
      "Alisher",
      "Muhammadali",
      "Sardor",
      "Azizbek",
      "Sherzod",
      "Jasurbek",
      "Aziz",
      "Bekzod",
      "Rustam",
      "Shahzod",
      "Otabek",
      "Akbar",
      "Dilshod",
      "Abdulloh",
      "Ulugbek",
      "Temurbek",
      "Akmal",
      "Miraziz",
      "Oybek",
      "Anvar"
    ],
    "common": [
      "Shoxrux",
      "Azamat",
      "Umar",
      "Timur",
      "Ibrohim",
      "Zafar",
      "Abdulaziz",
      "Sanjar",
      "Jamshid",
      "Dilmurod",
      "Doniyor",
      "Umid",
      "Zohid",
      "Shuxrat",
      "Muhammadyusuf",
      "Bobur",
      "Asilbek",
      "Ravshan",
      "Islom",
      "Alibek",
      "Javohir",
      "Muzaffar",
      "Firdavs",
      "Jahongir",
      "Farrux",
      "Sarvar",
      "Davron",
      "Ruslan",
      "Abror",
      "Jasur"
    ],
    "mid": [
      "Nodir",
      "Shavkat",
      "Ali",
      "Nodirbek",
      "Doston",
      "Elyor",
      "Jakhongir",
      "Fazliddin",
      "Murod",
      "Ivan",
      "Igor",
      "Bakhtiyor",
      "Abbos",
      "Shuhrat",
      "Ikrom",
      "Erkin",
      "Baxodir",
      "Bahodir",
      "Amir",
      "Abdulla",
      "Shakhzod",
      "Hamza",
      "Farhod",
      "Elbek",
      "Bahrom",
      "Muhammad",
      "Maruf",
      "Maksim",
      "Denis",
      "Bek",
      "Azim",
      "Shohruh",
      "Sardorbek",
      "Islombek",
      "Bekhzod",
      "Nuriddin",
      "Marat",
      "Mansur",
      "Javokhir",
      "Javlon",
      "Iskandar",
      "Farruh",
      "Botir",
      "Bahtiyor",
      "Anton",
      "Vadim",
      "Shukhrat",
      "Rasul",
      "Pavel",
      "Odil"
    ],
    "rare": [
      "Mukhammad",
      "Kirill",
      "John",
      "Jaloliddin",
      "Farrukh",
      "Damir",
      "Alex",
      "Akrom",
      "Sergey",
      "Said",
      "Max",
      "Jurabek",
      "Ilhom",
      "Elmurod",
      "Dilshodbek",
      "Abdumalik",
      "Sunnat",
      "Sherali",
      "Olimjon",
      "Olim",
      "Murodjon",
      "Laziz",
      "Husan",
      "Behzod",
      "Abdurahmon",
      "Umidjon",
      "Suxrob",
      "Sukhrob",
      "Sobir",
      "Sher",
      "Sanjarbek",
      "Samandar",
      "Rashid",
      "Mahmud",
      "Bakhrom",
      "Avaz",
      "Asror",
      "Abdurashid",
      "Yusuf",
      "Utkir",
      "Toxir",
      "Sarvarbek",
      "Ozod",
      "Mirjalol",
      "Lazizbek",
      "Konstantin",
      "Komil",
      "Kamoliddin",
      "Jonibek",
      "Hasan",
      "Furkat",
      "Farkhod",
      "Eldor",
      "Diyor",
      "Akram",
      "Vitaliy",
      "Uzbek",
      "Usmon",
      "Tolib",
      "Tim",
      "Stanislav",
      "Sirojiddin",
      "Shakhboz",
      "Pulat",
      "Odiljon",
      "Odilbek",
      "Obid",
      "Nurbek",
      "Murad",
      "Mirzohid",
      "Maksud",
      "Makhmud",
      "Leo",
      "Khusan",
      "Kamron",
      "Jamoliddin",
      "Jack",
      "Gayrat",
      "Don",
      "Dmitry",
      "Dmitriy",
      "Davronbek",
      "Bunyod",
      "Bobir",
      "Behruz",
      "Azizjon",
      "Azimjon",
      "Asadbek",
      "Asad",
      "Andrey",
      "Zarif",
      "Xurshed",
      "Xamza",
      "Victor",
      "Tohir",
      "Suhrob",
      "Shohjahon",
      "Sherzodbek",
      "Samad",
      "Salim",
      "Sadriddin",
      "Rahimjon",
      "Omar",
      "Nadir",
      "Mirshod",
      "Maqsud",
      "Mansurbek",
      "Khusniddin",
      "Khurshid",
      "Khumoyun",
      "Izzat",
      "Islomjon",
      "Iqboljon",
      "Ibragim",
      "Husniddin",
      "Hojiakbar",
      "Harry",
      "Hamid",
      "Fayzulla",
      "Fakhriddin",
      "David",
      "Daniel",
      "Boburbek",
      "Bob",
      "Bekhruz",
      "Asliddin",
      "Anvarbek",
      "Alim",
      "Alijon",
      "Alexey",
      "Akbarjon",
      "Ahror",
      "Adham",
      "Abdurahim"
    ]
  },
  "surnames": {
    "very_common": [
      "Karimov",
      "Yuldashev",
      "Abdullaev",
      "Yusupov",
      "Bek",
      "Umarov",
      "Sharipov",
      "Ergashev",
      "Rasulov",
      "Kim",
      "Ibragimov",
      "Abdullayev",
      "Usmonov",
      "Rustamov",
      "Usmanov",
      "Akhmedov",
      "Tursunov",
      "Sobirov",
      "Alimov",
      "Rahimov",
      "Nazarov",
      "Kurbanov",
      "Ismailov",
      "Makhmudov",
      "Rakhimov",
      "Qodirov",
      "Mahmudov",
      "Ahmedov",
      "Yunusov",
      "Yakubov",
      "Rashidov",
      "Khan",
      "Kasimov",
      "Akbarov",
      "Pulatov",
      "Muminov",
      "Azimov",
      "Olimov",
      "Mirzayev",
      "Ismoilov"
    ],
    "common": [
      "Hasanov",
      "Hakimov",
      "Gafurov",
      "Akramov",
      "Turgunov",
      "Saidov",
      "Raximov",
      "Rakhmatov",
      "Ochilov",
      "Maxmudov",
      "Madaminov",
      "Safarov",
      "Mirzaev",
      "Mamatov",
      "Khusanov",
      "Kadirov",
      "Ikromov",
      "Haydarov",
      "Axmedov",
      "Anvarov",
      "Iuldashev",
      "Sultonov",
      "Nosirov",
      "Kayumov",
      "Juraev",
      "Bozorov",
      "Bobojonov",
      "Aminov",
      "Kamolov",
      "Ismatov",
      "Islamov",
      "Djuraev",
      "Pak",
      "Shukurov",
      "Rahmonov",
      "Normatov",
      "Murodov",
      "Mirzo",
      "Mansurov",
      "Kholmatov",
      "Jabborov",
      "Isroilov",
      "Islomov",
      "Botirov",
      "Azizov",
      "Aliyev",
      "Iakubov",
      "Kadyrov",
      "Zokirov",
      "Zakirov",
      "Turaev",
      "Shokirov",
      "Shakirov",
      "Salimov",
      "Salikhov",
      "Raxmonov",
      "Mamadjanov",
      "Khasanov",
      "Khamidov",
      "Kamilov"
    ],
    "mid": [
      "Jurayev",
      "Jon",
      "Hamidov",
      "Ashurov",
      "Abduraimov",
      "Iusupov",
      "Khakimov",
      "Dzhuraev",
      "Xalilov",
      "Ubaydullaev",
      "Travel",
      "Ten",
      "Sultanov",
      "Soliyev",
      "Samandarov",
      "Sadikov",
      "Sabirov",
      "Oripov",
      "Nurmatov",
      "Nasirov",
      "Narzullaev",
      "Nabiev",
      "Mardonov",
      "Jalilov",
      "Fozilov",
      "Erkinov",
      "Aliev",
      "Abdurashidov",
      "Zufarov",
      "Zaripov",
      "Xamidov",
      "Toshtemirov",
      "Sidikov",
      "Sattarov",
      "Rakhmonov",
      "Rajabov",
      "Radjabov",
      "Nematov",
      "Mamadaliev",
      "Kurbonov",
      "Kudratov",
      "Komilov",
      "Jamolov",
      "Inoyatov",
      "Ikramov",
      "Hamdamov",
      "Ganiyev",
      "Fayziev",
      "Esanov",
      "Baratov",
      "Askarov",
      "Aripov",
      "Khamraev",
      "Masharipov",
      "Kosimov",
      "Israilov",
      "Ganiev",
      "Yuldoshev",
      "Xolmatov",
      "Xakimov",
      "Uzakov",
      "Urinov",
      "Turdiev",
      "Sodikov",
      "Shermatov",
      "Sharopov",
      "Samatov",
      "Said",
      "Ruzmetov",
      "Ruziev",
      "Rizayev",
      "Raxmatov",
      "Ravshanov",
      "Obidov",
      "Nur",
      "Nishonov",
      "Nigmatov",
      "Nasriddinov",
      "Muratov",
      "Muradov",
      "Mavlonov",
      "Man",
      "Maksudov",
      "Makhkamov",
      "Lee",
      "Khaydarov",
      "Khalikov",
      "Iskandarov",
      "Isaev",
      "Gulyamov",
      "Fayzullaev",
      "Babaev",
      "Azamov",
      "Aka",
      "Ahmad",
      "Abdurakhimov",
      "Abdurahmanov",
      "Abdukarimov",
      "Tsoi",
      "Khaidarov"
    ],
    "rare": [
      "Faiziev",
      "Sadykov",
      "Kodirov",
      "Zhuraev",
      "Aslanov",
      "Valiev",
      "Turayev",
      "Turakulov",
      "Tsoy",
      "Tour",
      "Temirov",
      "Talipov",
      "Star",
      "Siddikov",
      "Saydullaev",
      "Sattorov",
      "Sadiev",
      "Rich",
      "Rakhmanov",
      "Pérez",
      "Park",
      "Pardaev",
      "Otajonov",
      "Niyozov",
      "Niyazov",
      "Namozov",
      "Nabiyev",
      "Muzaffarov",
      "Mutalov",
      "Musayev",
      "Moon",
      "Matyakubov",
      "Matkarimov",
      "Matchanov",
      "Mamatqulov",
      "Mamatkulov",
      "Mamajonov",
      "Mamadaliyev",
      "Malikov",
      "Latipov",
      "Kuziev",
      "Kobilov",
      "Khayitov",
      "Kamalov",
      "Jumanov",
      "Jabbarov",
      "Isakov",
      "Hoshimov",
      "Hayitov",
      "Gofurov",
      "Fayziyev",
      "Djamalov",
      "Black",
      "Bazarov",
      "Batirov",
      "Babayan",
      "Asadov",
      "Amirov",
      "Amanov",
      "Allanazarov",
      "Agzamov",
      "Abdurahmonov",
      "Khodzhaev",
      "Khegai",
      "Khamdamov",
      "Khalilov",
      "Farmonov",
      "Tuichiev",
      "Raimov",
      "Radzhabov",
      "Mukhitdinov",
      "Musaev",
      "Moiseev",
      "Makhsudov",
      "Makarov",
      "Kuchkarov",
      "Dzhalalov",
      "Dzhabbarov",
      "Guliamov",
      "Bolotov",
      "Akhmedzhanov",
      "Abdurakhmanov",
      "Zoirov",
      "Yusupoff",
      "Yu",
      "Xoshimov",
      "Vaxobov",
      "Valiyev",
      "Usanov",
      "Uralov",
      "Umirov",
      "Tojiboyev",
      "Tohirov",
      "Tillaev",
      "Suyunov",
      "Shavkatov",
      "Sharapov",
      "Saparov",
      "Saliev",
      "Salaev",
      "Sadullaev",
      "Rizaev",
      "Raxmanov",
      "Rahmanov",
      "Nuriddinov",
      "Navruzov",
      "Nasimov",
      "Narzikulov",
      "Muxtarov",
      "Muxiddinov",
      "Muslimov",
      "Mannanov",
      "Malik",
      "Li",
      "Larson",
      "Khashimov",
      "Kabulov",
      "Kabilov",
      "Jamilov",
      "Halimov",
      "Halikov",
      "Gaziev",
      "Gaffarov",
      "Fazilov",
      "Eshmurodov",
      "Ermatov",
      "Egamov",
      "Djurabaev",
      "Davlatov",
      "Boboyev",
      "Bieber",
      "Bey",
      "Bazarbaev",
      "Avazov",
      "Atadjanov",
      "Angel",
      "Alibekov",
      "Akhmedjanov",
      "Ahmadjonov",
      "Ahmadi",
      "Abdusalomov",
      "Abdulloh",
      "Abdukadirov",
      "Iunusov",
      "Shevchenko",
      "Shashkov",
      "Khudoiarov",
      "Khudoiberdiev",
      "Kholmuradov",
      "Khodzhiev",
      "Khasanovich",
      "Khalimov",
      "Utkin",
      "Umerov",
      "Tukhtaev",
      "Tozhiev",
      "Tarasov",
      "Tagaev",
      "Subanov",
      "Sokolovich",
      "Sokolov",
      "Smirnov",
      "Safaev",
      "Rudenko",
      "Romanov",
      "Rakhmatillaev",
      "Poriadnikov",
      "Petrenko",
      "Perov",
      "Osmanov",
      "Nurov",
      "Nugmanov",
      "Norov",
      "Norboev",
      "Niiazov",
      "Nikolenko",
      "Nikolaev",
      "Nikitin",
      "Nizamov",
      "Negmatov",
      "Nasyrov",
      "Namazov",
      "Mukhtarov",
      "Mukhamedov",
      "Mel'nikov",
      "Medvedev",
      "Mamedov",
      "Mamadzhanov",
      "Lebed'",
      "Lebedev",
      "Lazarev",
      "Kurov",
      "Kuz'min",
      "Kravchenko",
      "Kostiuchenko",
      "Kozak",
      "Kaiumov",
      "Kakhkharov",
      "Karabaev",
      "Kan",
      "Irgashev",
      "Il'iasov",
      "Ziiatov",
      "Zakharov",
      "Zaretskaia",
      "Zhumaniiazov",
      "Zhukov",
      "Egorov",
      "Drozdov",
      "Dmitriev",
      "Vakhobov",
      "Vasil'ev",
      "Baltaev",
      "Babaian",
      "Achilov",
      "Akhmediev",
      "Atabaev",
      "Artykov",
      "Andreev",
      "Abramian",
      "Abramkin",
      "Zairov",
      "Zaim",
      "Yusupjanov",
      "Yadgarov",
      "Xurramov",
      "Xatamov",
      "Xamraev",
      "Xamdamov",
      "Washington",
      "Vakhabov",
      "Usman",
      "Usarov",
      "Urmanov",
      "Urakov",
      "Umurzakov",
      "Turner",
      "Turgunboev",
      "Toyirov",
      "Toshmatov",
      "Toirov",
      "Togaev",
      "Tashpulatov",
      "Tashmatov",
      "Tairov",
      "Tahirov",
      "Sulton",
      "Sultan",
      "Suleymanov",
      "Soliev",
      "Short",
      "Shoh",
      "Shodiev",
      "Shirov",
      "Shin",
      "Sherov",
      "Sher",
      "Sharif",
      "Shamuratov",
      "Shamsiev",
      "Shams",
      "Shadiev",
      "Severino",
      "Sayf",
      "Sarimsakov",
      "Saparbaev",
      "Sapaev",
      "Samiev",
      "Salomov",
      "Sagdiev",
      "Safari",
      "Sadriddinov",
      "Sadirov",
      "Ruzmatov",
      "Ruzikulov",
      "Ronaldo",
      "Ren",
      "Razakov",
      "Ray",
      "Rasul",
      "Rashitov",
      "Ramazonov",
      "Ramazanov",
      "Rahmon",
      "Rahim",
      "Radjapov",
      "Print",
      "Prince",
      "Popov",
      "Peralta",
      "Osman",
      "Nurullaev",
      "Nurmetov",
      "Nuritdinov",
      "Nuñez",
      "Numonov",
      "Norkulov",
      "Nazirov",
      "Nazimov",
      "Navo",
      "Muydinov",
      "Mustafayev",
      "Mukimov",
      "Muhamedov",
      "Montana",
      "Mirzabaev",
      "Mirzaahmedov",
      "Minier",
      "Messi",
      "Meliboev",
      "Mclaren",
      "Marufov",
      "Mari",
      "Mardanov",
      "Mamurov",
      "Mamarasulov",
      "Makarenko",
      "Majidov",
      "Madrid",
      "Lyan",
      "López",
      "Little",
      "Lim",
      "Lazizov",
      "Kogay",
      "Ko",
      "Kholbaev",
      "Khegay",
      "Kenjaev",
      "Kazakov",
      "Kaya",
      "Kay",
      "Katkov",
      "Karshiev",
      "Karim",
      "Kariev",
      "Jumaev",
      "Jamoldinov",
      "Isayev",
      "Irismetov",
      "Inomov",
      "Ibra",
      "Ibatov",
      "Husanov",
      "Husainov",
      "Hill",
      "Heart",
      "Han",
      "Halilov",
      "Gaybullaev",
      "Gafurjanov",
      "Gafforov",
      "Fayz",
      "Erimbetov",
      "Ergashov",
      "Egamberdiev",
      "Djalilov",
      "Djalalov",
      "Diaz",
      "Decor",
      "Dastan",
      "Dar",
      "Daminov",
      "Dadashev",
      "Dadabaev",
      "Cohen",
      "Cid",
      "Choi",
      "Che",
      "Buriev",
      "Burhanov",
      "Bonura",
      "Bonu",
      "Boltaev",
      "Boboev",
      "Bob",
      "Berdiev",
      "Bekov",
      "Bekmanov",
      "Bekbergenov",
      "Begaliev",
      "Becker",
      "Beck",
      "Baraka",
      "Bakoev",
      "Badalyants",
      "Badalbaev",
      "Aziz",
      "Azim",
      "Azamatov",
      "Axunjanov",
      "Axtamov",
      "Avezov",
      "Atamuratov",
      "Atajanov",
      "Asimov",
      "Art",
      "Arapov",
      "Arabov",
      "Anarkulov",
      "Amonov",
      "Allaberganov",
      "Alim",
      "Alijonov",
      "Alibaev",
      "Adilov",
      "Abilov",
      "Abidov",
      "Abduvaliyev",
      "Abduraxmonov",
      "Abduraxmanov",
      "Abduraximov",
      "Abdunazarov",
      "Abdukodirov",
      "Abdiev",
      "Iakh'iaev",
      "Iakhioev",
      "Iarovoi",
      "Iarmukhamedov",
      "Ianov",
      "Iangazov",
      "Ialalov",
      "Iakoventsev",
      "Iakimtsev",
      "Iazvetsov",
      "Iutkin",
      "Ius'kiv",
      "Iurkovets",
      "Iulchiev",
      "Iugai",
      "Eshonkulov",
      "Eminov",
      "Shcherbakov",
      "Shutko",
      "Shumilo",
      "Shumakov",
      "Shul'gin",
      "Shtapov",
      "Shoshin",
      "Shmakov",
      "Shliakhtin",
      "Shishko",
      "Shinkevich",
      "Shekhovtsov",
      "Shegai",
      "Shvets",
      "Sharov",
      "Sharaev",
      "Shamirzaev",
      "Shalda",
      "Shagoian",
      "Chukharev",
      "Choriev",
      "Chirkov",
      "Chimaev",
      "Chik",
      "Chernogaev",
      "Chernikov",
      "Cherednichenko",
      "Charyev",
      "Chaikovskii",
      "Tsybul'skii",
      "Tsukanov",
      "Tsarev",
      "Khusainov",
      "Khuzhaev",
      "Khudik",
      "Khoshimov",
      "Khorunov",
      "Khoroshun",
      "Khomiak",
      "Khomitskaia",
      "Kholboev",
      "Khisamutdinov",
      "Khidoiatov",
      "Kheruvimov",
      "Khvan",
      "Khaiatov",
      "Khatamov",
      "Khamrokulov",
      "Khamrakulov",
      "Khalmatov",
      "Khalitov",
      "Khaknazarov",
      "Khakimzhanov",
      "Khaikin",
      "Khaiitov",
      "Fediukovich",
      "Fedorov",
      "Fedorenko",
      "Fadeev",
      "Ushakov",
      "Utenev",
      "Uteev",
      "Ustinenko",
      "Urunov",
      "Urunbaev",
      "Uzbekov",
      "Udnikov",
      "Uvarov",
      "Ubaidullaev",
      "Tian",
      "Tiutiunikov",
      "Tushev",
      "Tutaev",
      "Turianitsia",
      "Turdikulov",
      "Turganbaev",
      "Tugalov",
      "Trunov",
      "Tochilin",
      "Topchii",
      "Tonitsoi",
      "Tkachenko",
      "Timoshenko",
      "Timirgaliev",
      "Teterev",
      "Tereshchenko",
      "Teriokhin",
      "Terenin",
      "Tekeev",
      "Tedeev",
      "Tatarintsev",
      "Taratuta",
      "Talachev",
      "Tadzhiev",
      "Tadzhibaev",
      "Tagirov",
      "Sukhonogov",
      "Sukhov",
      "Sukhar'",
      "Surov",
      "Sumskoi",
      "Sultanovich",
      "Sulaimanov",
      "Subkhankulov",
      "Stepanov",
      "Spiridonov",
      "Spivak",
      "Sotkov",
      "Sotarev",
      "Sosnitskii",
      "Sorokin",
      "Soliars'kii",
      "Soldatov",
      "Smoliachenko",
      "Slobodchikov",
      "Slin'ko",
      "Slepov",
      "Sladkii",
      "Slavikov",
      "Skorobogatov",
      "Skokov",
      "Sitdikov",
      "Simonov",
      "Seredich",
      "Serdiuk",
      "Sergeevich",
      "Sergeev",
      "Senchenko",
      "Semeniuk",
      "Semionov",
      "Seliutin",
      "Selezniov",
      "Sekret",
      "Seitosmanov",
      "Sevast'ian",
      "Sakhabutdinov",
      "Safin",
      "Sarsenov",
      "Sapozhnikov",
      "Sanzharov",
      "Samokhin",
      "Samardak",
      "Salogub",
      "Salenko",
      "Salei",
      "Salamov",
      "Saidullaev",
      "Saitov",
      "Saitkulov",
      "Saenko",
      "Savchuk",
      "Savchenko",
      "Savitskaia",
      "Savenkov",
      "Rumiantsev",
      "Romashko",
      "Romashin",
      "Romanovskii",
      "Roman",
      "Risovanyi",
      "Red'kin",
      "Rakhmatullaev",
      "Rakhimdzhanov",
      "Raupov",
      "Razhapov",
      "Razhabov",
      "Radionov",
      "Pushnin",
      "Prosvirkin",
      "Pronoza",
      "Proezdov",
      "Primkulov",
      "Potylitsyna",
      "Potoroka",
      "Poruchikov",
      "Ponomarenko",
      "Polianichko",
      "Polozkov",
      "Poleiko",
      "Podgornaia",
      "Pogrebniak",
      "Pliushkov",
      "Pishchulin",
      "Pisarenko",
      "Pisarev",
      "Piloian",
      "Pilipenko",
      "Petrovykh",
      "Pernitskaia",
      "Pereviazko",
      "Perevertailo",
      "Pashkov",
      "Parashchenko",
      "Pantusevich",
      "Panteleev",
      "Pankovets",
      "Pan",
      "Pavliuchenko",
      "Pavlenko",
      "Otazhonov",
      "Ostrovskii",
      "Orlovskii",
      "Omel'chenko",
      "Omarov",
      "Oliinik",
      "Ovsiukov",
      "Obas'kin",
      "Nurmukhamedov",
      "Nurmanov",
      "Nuriev",
      "Nurdinov",
      "Nuraliev",
      "Narkulov",
      "Narziev",
      "Nam",
      "Naimov",
      "Nagai",
      "Nabeev",
      "Nikolaichuk",
      "Mukhsinov",
      "Mukhitov",
      "Mukhiddinov",
      "Mukhametshin",
      "Mukhamedzhanov",
      "Mutovin",
      "Mutalibov",
      "Mustafin",
      "Mustafa",
      "Musin",
      "Musalov",
      "Murtazaliev",
      "Murtazaev",
      "Murin",
      "Murav'ev",
      "Mukminov",
      "Muzhdabaev",
      "Mubashirov",
      "Motornyi",
      "Moroz",
      "Morzhov",
      "Mitrokhin",
      "Mis'ko",
      "Mironchik",
      "Mirkasimov",
      "Mirzoev",
      "Mirzaakhmedov",
      "Milaia",
      "Mizernyi",
      "Mel'nik",
      "Melov",
      "Medik",
      "Mashkovtsev",
      "Mats'kevich",
      "Matusevich",
      "Matnazarov",
      "Matmusaev",
      "Martynenko",
      "Mardiev",
      "Manukian",
      "Manzurov",
      "Mamontov",
      "Mamirov",
      "Mambetov",
      "Mamarakhimov",
      "Maliuta",
      "Malyshev",
      "Malkin",
      "Malanin",
      "Maksumov",
      "Maksim",
      "Maiboroda",
      "Mazurenko",
      "Madrakhimov",
      "Magdiev",
      "Magamedov",
      "Mavlianov",
      "Lian",
      "Liushnenko",
      "Luchnikov",
      "Los'",
      "Lomanov",
      "Lomakin",
      "Lobantsev",
      "Litvinov",
      "Litvin",
      "Linchuk",
      "Leont'ev",
      "Leonenko",
      "Lashko",
      "Lazurenko",
      "Kuchmar",
      "Kucherov",
      "Kusov",
      "Kuramshin",
      "Kuralin",
      "Kunakbaev",
      "Kulik",
      "Kuznitsov",
      "Kuznetsov",
      "Kudriavtsev",
      "Krupko",
      "Kramor",
      "Kramer",
      "Kravchik",
      "Koshkarov",
      "Kochkin",
      "Kos'ianenko",
      "Kostiuk",
      "Kostychev",
      "Kostrov",
      "Kostin",
      "Kostiv",
      "Koriachkin",
      "Kortunov",
      "Korol'",
      "Korobkin",
      "Kopytov",
      "Kopeikin",
      "Kontiukov",
      "Konnov",
      "Komarov",
      "Kolodiazhnyi",
      "Koldun",
      "Kolbin",
      "Kozoriz",
      "Kozlovskii",
      "Kozlovskaia",
      "Kozlenko",
      "Kozhevnikov",
      "Kogai",
      "Kovin",
      "Koval'chuk",
      "Koval'",
      "Kovalishin",
      "Kovaliov",
      "Kobtsev",
      "Kobets",
      "Klychev",
      "Kisliuk",
      "Kislykh",
      "Kiseliov",
      "Kirichev",
      "Kii",
      "Kienko",
      "Kenzhaev",
      "Kebadze",
      "Kakhramanov",
      "Kakharov",
      "Katiushka",
      "Katrin",
      "Kasparov",
      "Karpuk",
      "Karpenko",
      "Karev",
      "Kardashev",
      "Kardash",
      "Karataev",
      "Karavan",
      "Karavaev",
      "Kandinov",
      "Kamyshanskaia",
      "Kalugin",
      "Kalashnikov",
      "Kadyrkulov",
      "Kadyrbaev",
      "Ishkhanov",
      "Ishbaev",
      "Ishanov",
      "Isoev",
      "Ismanov",
      "Isipov",
      "Irgashov",
      "Il'chuk",
      "Il'chenko",
      "Il'enko",
      "Izmailov",
      "Izatullaev",
      "Igamberdiev",
      "Ivashchenko",
      "Ibadullaev",
      "Ziabbarov",
      "Zyrianov",
      "Zubov",
      "Zubachenko",
      "Zolotykh",
      "Zolotukhin",
      "Zolotov",
      "Ziiaev",
      "Zimniakov",
      "Zimin",
      "Zenkov",
      "Zakhidov",
      "Zakhvatov",
      "Zakhartsev",
      "Zainiev",
      "Zaika",
      "Zaitov",
      "Zaikin",
      "Zagrebin",
      "Zavadskaia",
      "Zabolotskikh",
      "Zhurakovskii",
      "Zhumanov",
      "Zhumaev",
      "Zhumabaev",
      "Zhirokhov",
      "Zhilikhovs'kii",
      "Zhidov",
      "Zheltukhin",
      "Zheleznyi",
      "Zharov",
      "Zharkov",
      "Zhamalov",
      "Zhamalitdinov",
      "Zhalilov",
      "Zhak",
      "Zhabbarov",
      "Efimov",
      "Ershov",
      "Ermakov",
      "Eremian",
      "Enbulaev",
      "Elshin",
      "Elizarov",
      "Iokubov",
      "Egiazarian",
      "Evdokimov",
      "Dubasov",
      "Dotsenko",
      "Dorokhin",
      "Donets",
      "Domozhirov",
      "Dmitrievich",
      "Dzhumaev",
      "Dzhalilov",
      "Dzhabarov",
      "Dereviashkin",
      "Dergachiov",
      "Deinega",
      "Deev",
      "Degai",
      "Dvurechenskii",
      "Daniliuk",
      "Damaskin",
      "Davydovich",
      "Davranov",
      "Davliatov",
      "Guseinov",
      "Gurskaia",
      "Guriliov",
      "Gumirov",
      "Gumerov",
      "Guliaev",
      "Guliavin",
      "Gul'basov",
      "Gulamov",
      "Gubar'",
      "Gubarev",
      "Gubanov",
      "Griazin",
      "Grishkevich",
      "Grishin",
      "Grigorian",
      "Grigorov",
      "Grachev",
      "Gosudarev",
      "Gostiukhin",
      "Gorozhankin",
      "Golubitskii",
      "Goloma",
      "Golodriga",
      "Golikov",
      "Goldobin",
      "Goza",
      "Glukhikh",
      "Gizatov",
      "Gevondian",
      "Gasimov",
      "Garifullin",
      "Garaev",
      "Gapparov",
      "Gamaiunov",
      "Galstian",
      "Galimzianov",
      "Galata",
      "Galaktionov",
      "Gazarian",
      "Vysotskaia",
      "Vorob'iov",
      "Volkonskii",
      "Volkov",
      "Vladimirovich",
      "Vladimirov",
      "Vishniakov",
      "Vinogradov",
      "Viktorovich",
      "Vetokhin",
      "Verin",
      "Velichko",
      "Velikii",
      "Veliev",
      "Vakhidov",
      "Vafaev",
      "Variukhin",
      "Varkulevich",
      "Varkov",
      "Vanin",
      "Bykov",
      "Byvshev",
      "Bukharskii",
      "Burman",
      "Bul'ba",
      "Bulgakov",
      "Bronnikov",
      "Brovkov",
      "Bratukhin",
      "Bragin",
      "Bochkarev",
      "Borisenkov",
      "Bondarenko",
      "Boikov",
      "Boiko",
      "Bobrovskaia",
      "Bobokhonov",
      "Bliznetsov",
      "Bernik",
      "Berezhnoi",
      "Berezhnov",
      "Beregov",
      "Berber",
      "Beliakov",
      "Belov",
      "Belenko",
      "Bektashev",
      "Beknazarov",
      "Bekmirzaev",
      "Bezrodnyi",
      "Beglov",
      "Bashirov",
      "Bakhtiiarov",
      "Bakhtigareev",
      "Bakhriev",
      "Batiushkov",
      "Batyrov",
      "Batarchuk",
      "Baryshnikov",
      "Bartosh",
      "Barnaev",
      "Barannikov",
      "Banatov",
      "Baltabaev",
      "Balenkov",
      "Balaian",
      "Bakaev",
      "Baibekov",
      "Badalian",
      "Badalov",
      "Bagretsov",
      "Bagiev",
      "Bagdavadze",
      "Babaiants",
      "Babakhanov",
      "Bilous",
      "Bilins'kii",
      "Akhunov",
      "Akhundzhanov",
      "Akhmatov",
      "Afrin",
      "Ataev",
      "Atadzhanov",
      "Atabekov",
      "Asatov",
      "Arkhipov",
      "Arkhangel'skii",
      "Artikov",
      "Artiom",
      "Arsenin",
      "Aristov",
      "Aniskin",
      "Andreichenko",
      "Anarbaev",
      "Amosov",
      "Aminev",
      "Amin",
      "Ametov",
      "Aliakrinskaia",
      "Al'bert",
      "Alimzhanov",
      "Alimbaev",
      "Alizhanov",
      "Aleksandrov",
      "Alaudinov",
      "Akmalov",
      "Akif'ev",
      "Aitenov",
      "Adylov",
      "Agabekian",
      "Abrarov",
      "Ablazhevich",
      "Abdukhalimov",
      "Abdukhakimov",
      "Abdurakhmonov",
      "Abdurazakov",
      "Abdulakhatov",
      "Abdukadyrov",
      "Abbiasov",
      "Abbasov",
      "Zuparov",
      "Zubarev",
      "Zoda",
      "Ziyatdinov",
      "Zhang",
      "Zayn",
      "Zaxar",
      "Zarifov",
      "Zar",
      "Zakir",
      "Zaki",
      "Zain",
      "Zagorenko",
      "Zafarov",
      "Zafar",
      "Yusufov",
      "Yusuf",
      "Yushchenko",
      "Yunusmetov",
      "Yunus",
      "Yugay",
      "Yonts",
      "Yen",
      "Yawar",
      "Yatman",
      "Yasin",
      "Yale",
      "Yaghoubi",
      "Yablonskaya",
      "Xusanov",
      "Xusanbaev",
      "Xusainov",
      "Xomidov",
      "Xolov",
      "Xolmurodov",
      "Xodjakov",
      "Xing",
      "Xidirov",
      "Xaus",
      "Xasanov",
      "Xamroev",
      "Xabibullaev",
      "Wurpel",
      "Wren",
      "Wonka",
      "Wong",
      "Wolf",
      "Woh",
      "Witts",
      "Wise",
      "Winfrey",
      "Winchester",
      "Win",
      "Willson",
      "Wilbur",
      "Wheeler",
      "Weitzman",
      "Wedding",
      "Webster",
      "Web",
      "Wayte",
      "Wave",
      "Warburton",
      "Wap",
      "Walter",
      "Wallace",
      "Wall",
      "Waldon",
      "Waddingham",
      "Vox",
      "Volos",
      "Voitov",
      "Vlashin",
      "Vita",
      "Villarreal",
      "Vermeulen",
      "Velo",
      "Velasco",
      "Vecchietti",
      "Vasques",
      "Vasiev",
      "Vasallo",
      "Vartanyan",
      "Varava",
      "Vandenbusch",
      "Van Dijck",
      "Vaisov",
      "Vahabov",
      "Vahab",
      "Uzbek",
      "Useinov",
      "Urokov",
      "Urbaez",
      "Urazbaev",
      "Urazaliev",
      "Uraev",
      "Unit",
      "Ummatov",
      "Umi",
      "Umaraliev",
      "Ulugov",
      "Ulashev",
      "Tyo",
      "Tyan",
      "Tuychiyev",
      "Tuxtaev",
      "Turkov",
      "Turkmenov",
      "Türkmen",
      "Türker",
      "Türkel",
      "Turan",
      "Turabekov",
      "Tumanov",
      "Tuckey",
      "Tsay",
      "Trubitsin",
      "Trogen",
      "Travin",
      "Train",
      "Trade",
      "Toxirov",
      "Tovari",
      "Tours",
      "Tores",
      "Toprak",
      "Tomlinson",
      "Tomalak",
      "Tiwary",
      "Tip",
      "Tilki",
      "Tigers",
      "Tia",
      "Thapa",
      "Teshaboev",
      "Teshabaev",
      "Telmanov",
      "Tei",
      "Tehrani",
      "Teacher",
      "Tea",
      "Tawab",
      "Taveras",
      "Tavarez",
      "Tav",
      "Tashtemirov",
      "Tash",
      "Tarantino",
      "Tangriberganov",
      "Taj",
      "Tagiyev",
      "Tae",
      "Tador",
      "Tadeush",
      "Sweet",
      "Suvanov",
      "Sushi",
      "Suponov",
      "Sun",
      "Summer",
      "Sultana",
      "Sulemin",
      "Sulaman",
      "Sukhi",
      "Stroy",
      "Strautin",
      "Straube",
      "Strashnikov",
      "Stotko",
      "Stone",
      "Stitou",
      "Stevenson",
      "Steil",
      "Stark",
      "Stanislav",
      "Stand",
      "Stan",
      "Stacey",
      "Sson",
      "Spurs",
      "Spirit",
      "Spacey",
      "Sözer",
      "Soylu",
      "Sotvoldiev",
      "Sönmez",
      "Song",
      "Son",
      "Solod",
      "Soleev",
      "Soiko",
      "Snyder",
      "Snow",
      "Smit",
      "Smile",
      "Skupien",
      "Sklyarov",
      "Skichko",
      "Singh",
      "Singer",
      "Simpkins",
      "Siddik",
      "Shuin",
      "Shubin",
      "Shpakov",
      "Shox",
      "Shot",
      "Shomirzaev",
      "Shirinov",
      "Shirin",
      "Sherzad",
      "Sherwood",
      "Shermetov",
      "Sherbakov",
      "Shek",
      "Shein",
      "Shea",
      "Shay",
      "Shaxmamedov",
      "Shax",
      "Sharifov",
      "Sharafutdinov",
      "Shamsidinov",
      "Shametov",
      "Shahzad",
      "Shahida",
      "Shady",
      "Shadmanov",
      "Shabonov",
      "Seyfi",
      "Sevigny",
      "Serch",
      "Şen",
      "Sednenko",
      "Seal",
      "Scofield",
      "School",
      "Scholfield",
      "Schneidman",
      "Schneider",
      "Schlicht",
      "Sawa",
      "Satimov",
      "Sati",
      "Sasha",
      "Sarvari",
      "Sarvardinov",
      "Sarsenbaev",
      "Sarı",
      "Saremi",
      "Sara",
      "Sapov",
      "Sankar",
      "Sangster",
      "Sandoval",
      "Sanchez",
      "Sanaev",
      "Sampson",
      "Sammy",
      "Saminov",
      "Samedov",
      "Samael",
      "Samadov",
      "Salom",
      "Salmanov",
      "Salihov",
      "Salih",
      "Salah",
      "Saint",
      "Saidani",
      "Sagatov",
      "Safoev",
      "Safiev",
      "Safe",
      "Safarzoda",
      "Safaraliev",
      "Saeed",
      "Sadritdinov",
      "Sadovskaya",
      "Sadeghi",
      "Sabr",
      "Sabitov",
      "Sabancı",
      "Saban",
      "Saatov",
      "Saakyan",
      "Saakov",
      "Rzaev",
      "Ruzibaev",
      "Rustam",
      "Rudd",
      "Rozmetov",
      "Rozikov",
      "Rower",
      "Rose",
      "Roš",
      "Rooney",
      "Ronning",
      "Ron",
      "Romeo",
      "Rodrigues",
      "Rodgers",
      "Robertz",
      "Roben",
      "Rizo",
      "Rine",
      "Rimas",
      "Rigo",
      "Ricardo",
      "Ribkin",
      "Reznikov",
      "Reyes",
      "Revera",
      "Resül",
      "Reshitov",
      "Reshetov",
      "Rem",
      "Reed",
      "Redondo",
      "Redon",
      "Razikov",
      "Razik",
      "Razi",
      "Raxmatullaev",
      "Ravzutdinov",
      "Rauf",
      "Rasulev",
      "Rashid",
      "Rasa",
      "Rand",
      "Ramos",
      "Ramone",
      "Ramizov",
      "Ramirez",
      "Rajawi",
      "Ràjã",
      "Raiz",
      "Rais",
      "Rain",
      "Quinn",
      "Quddus",
      "Qayum",
      "Putin",
      "Pumpe",
      "Pulotov",
      "Public",
      "Primov",
      "Prime",
      "Price",
      "Press",
      "Prenov",
      "Praha",
      "Powell",
      "Portenko",
      "Polo",
      "Polanco",
      "Poison",
      "Pogosov",
      "Pizza",
      "Pizarro",
      "Pivovarov",
      "Pirmatov",
      "Pinkard",
      "Piddock",
      "Pete",
      "Perry",
      "Perci",
      "Peñaló",
      "Pellicer",
      "Pearson",
      "Pearl",
      "Paulson",
      "Pashkovskiy",
      "Parson",
      "Parpiyev",
      "Parpiev",
      "Papadopoulos",
      "Panezai",
      "Panda",
      "Panagiotis",
      "Palvanov",
      "Palagin",
      "Paint",
      "Paetzold",
      "Ozil",
      "Ozgur",
      "Ozdemir",
      "Owens",
      "Otaev",
      "Otaboev",
      "Osmany",
      "Ortikov",
      "Ortega",
      "Orolov",
      "Orlov",
      "Orient",
      "Opaev",
      "Ong",
      "Önçırak",
      "Ömür",
      "Omon",
      "Ömer",
      "Olin",
      "Olevsky",
      "Ojo",
      "Ogden",
      "Odam",
      "Obidjonov",
      "O'beirne",
      "Nuridinov",
      "Nuratdinov",
      "Nozi",
      "Noza",
      "Noshadi",
      "Nor",
      "Nogay",
      "Noel",
      "Nock",
      "Nizomov",
      "Nizamiev",
      "Nishanov",
      "Nikolay",
      "Nik",
      "Nigmanov",
      "Nickolay",
      "Nichol",
      "Nezam",
      "Newman",
      "Net",
      "Nepsha",
      "Nazaroff",
      "Nazar",
      "Naumov",
      "Naumenko",
      "Nasrullaev",
      "Nasridinov",
      "Narimanov",
      "Nana",
      "Name",
      "Nahimov",
      "Nagay",
      "Nagaraj",
      "Nadjimov",
      "Nadirov",
      "Naceri",
      "Nabi",
      "Muzaffar",
      "Muzafarov",
      "Muxsinov",
      "Muxammadiev",
      "Mutaliev",
      "Mustafakulov",
      "Mustafaev",
      "Muso",
      "Muslim",
      "Mursaliev",
      "Murod",
      "Murad",
      "Munteanu",
      "Munir",
      "Mullet",
      "Mullane",
      "Mulla",
      "Mukhtar",
      "Mukhammadiev",
      "Muhammadov",
      "Muhammadi",
      "Muhammadali",
      "Mubinov",
      "Mosheev",
      "Mosavi",
      "Morrissey",
      "Mori",
      "Moreno",
      "Moosavinia",
      "Molly",
      "Mohamoud",
      "Moeini",
      "Mobile",
      "Mirzaliyev",
      "Mirzaliev",
      "Mirzakarimov",
      "Mirzaee",
      "Mirzabekov",
      "Mirxadiev",
      "Mirsaidov",
      "Mirle",
      "Mirakhmedov",
      "Mira",
      "Mir",
      "Mings",
      "Min",
      "Milian",
      "Milano",
      "Mikhaylov",
      "Mice",
      "Merkel",
      "Mercadante",
      "Menshikov",
      "Meng",
      "Mendez",
      "Melsov",
      "Melikulov",
      "Melikov",
      "Meliev",
      "Mehan",
      "Mechanic",
      "Mcquain",
      "Mcnally",
      "Mcmullen",
      "Mclaughlan",
      "Mcgregor",
      "Mccune",
      "Mccool",
      "Mcconn",
      "Mcallister",
      "Mazhar",
      "Maynor",
      "May",
      "Maxsudov",
      "Maxmaev",
      "Maxkamov",
      "Maxi",
      "Maxanov",
      "Mavlyanov",
      "Matvienko",
      "Maslov",
      "Maskani",
      "Maruf",
      "Martinsson",
      "Marleen",
      "Marks",
      "Markov",
      "Markin",
      "Marg",
      "Maratov",
      "Mar",
      "Manov",
      "Mannapov",
      "Mann",
      "Mani",
      "Mandi",
      "Mamutov",
      "Mammadzade",
      "Mametov",
      "Mamadou",
      "Malino",
      "Maksakov",
      "Makridin",
      "Makhloufi",
      "Maker",
      "Mak",
      "Mahmoodi",
      "Mahendra",
      "Magzumov",
      "Magomedov",
      "Magee",
      "Maer",
      "Madraximov",
      "Madrahimov",
      "Madiyev",
      "Madatov",
      "Madaliev",
      "Mactavish",
      "Macsim",
      "Macnair",
      "Macgregor",
      "Macaulay",
      "Ma",
      "Lysenkov",
      "Lunch",
      "Luna",
      "Lukyanov",
      "Luiza",
      "Luiz",
      "Lucky",
      "Lovett",
      "Lovato",
      "Loud",
      "London",
      "Lola",
      "Lofthouse",
      "Lofstrom",
      "Live",
      "Lis",
      "Lion",
      "Limpio",
      "Limoli",
      "Like",
      "Levo",
      "Leung",
      "Letal",
      "Lester",
      "Lennon",
      "Leconte",
      "Lazzaoui",
      "Lave",
      "Lavalley",
      "Latgé",
      "Lasa",
      "Lanthier",
      "Langeland",
      "Land",
      "Lad",
      "Kuts",
      "Kushanov",
      "Kushaev",
      "Kush",
      "Kurmanov",
      "Kurmaev",
      "Kurambaev",
      "Kumari",
      "Kumar",
      "Kulikov",
      "Kuliev",
      "Kuldashev",
      "Kulagin",
      "Kukushka",
      "Kudashkin",
      "Kruglov",
      "Kruchinin",
      "Kralovec",
      "Kozlov",
      "Korovin",
      "Korotin",
      "Koriev",
      "Koppala",
      "Komoldinov",
      "Kolesnikov",
      "Kolarov",
      "Kojima",
      "Kogaj",
      "Kodenko",
      "Kocaman",
      "Knyazev",
      "Klinner",
      "Klimov",
      "Kirakosyan",
      "Kips",
      "Khuja",
      "Khon",
      "Khodja",
      "Khidirov",
      "Kharlamoff",
      "Khardi",
      "Khammassi",
      "Khalily",
      "Khalil",
      "Khali",
      "Khal",
      "Khaitov",
      "Kha",
      "Keyes",
      "Kerimov",
      "Kemp",
      "Kelly",
      "Keelaghan",
      "Kazakbaev",
      "Kato",
      "Kate",
      "Kataev",
      "Kasymov",
      "Kasper",
      "Kashubin",
      "Karayev",
      "Karapetyan",
      "Karagoz",
      "Karagodin",
      "Kamgar",
      "Kamardinov",
      "Kalandarov",
      "Kaharov",
      "Jørgensen",
      "Jumayev",
      "Jumaniyozov",
      "Julianna",
      "Judo",
      "Jolie",
      "Jokker",
      "Jokes",
      "Jimenez",
      "Jia",
      "Jha",
      "Jenkins",
      "Jeen",
      "Jaymes",
      "Jay",
      "Jawaid",
      "Jasmin",
      "Jan",
      "Jamalov",
      "Jain",
      "Jagi",
      "Jafarov",
      "Jaeger",
      "Jaber",
      "Isxakov",
      "Ismailoff",
      "Ismail",
      "Islam",
      "Iskhakov",
      "Ishimov",
      "Iovenko",
      "Inn",
      "Indian",
      "Inal",
      "Imamov",
      "Ilikov",
      "Iglesias",
      "Iftikhar",
      "Idol",
      "Ice",
      "Ibrahimov",
      "Hutchings",
      "Hurtado",
      "Hunt",
      "Huja",
      "Howard",
      "House",
      "Hotel",
      "Hossain",
      "Hook",
      "Homidov",
      "Holland",
      "Hikmati",
      "Herrera",
      "Hernandéz",
      "Hermandez",
      "Henriquez",
      "Hellier",
      "Hegay",
      "Head",
      "Haymaker",
      "Hayat",
      "Havasi",
      "Hatip",
      "Hasan",
      "Hart",
      "Hariton",
      "Hanum",
      "Hanske",
      "Hanim",
      "Hanachi",
      "Hamza",
      "Hammond",
      "Hamid",
      "Haghighi",
      "Haci",
      "Habibov",
      "Guzal",
      "Guven",
      "Gutierrez",
      "Gural",
      "Gunn",
      "Gulsun",
      "Gul",
      "Guijosa",
      "Grosso",
      "Grin",
      "Grigoryan",
      "Greenhouse",
      "Grebenyuk",
      "Graumann",
      "Gram",
      "Gottfried",
      "Gorodov",
      "Gorod",
      "Gören",
      "Gomez",
      "Gomer",
      "Golubev",
      "Gold",
      "Goh",
      "Glad",
      "Gizatullin",
      "Giyosov",
      "Gift",
      "Ghost",
      "Ghinami",
      "German",
      "Georgiadu",
      "Gazarov",
      "Gavrilin",
      "Gauge",
      "Garri",
      "Garra",
      "Garner",
      "Garipov",
      "Garifulin",
      "Garfield",
      "Gapurov",
      "Gannon",
      "Ganeev",
      "Gallegos",
      "Galimov",
      "Galiev",
      "Galenko",
      "Gaipov",
      "Gagarin",
      "Gaforov",
      "Gadaev",
      "Gabarra",
      "Fuat",
      "Frolov",
      "Freud",
      "Fraser",
      "Fox",
      "Foto",
      "Foster",
      "Fortuny",
      "Forbs",
      "Flooks",
      "Fitzgerald",
      "Fishman",
      "Fiori",
      "Filonenko",
      "Film",
      "Fillmore",
      "Filatov",
      "Fil",
      "Figueres",
      "Figueiredo",
      "Fetrat",
      "Fetisov",
      "Fendi",
      "Fefelov",
      "Fedotov",
      "Fedoseenko",
      "Fedirtsan",
      "Fazil",
      "Fayez",
      "Faxriev",
      "Farrukh",
      "Faris",
      "Faridov",
      "Fall",
      "Eyes",
      "Espinal",
      "Eshpulatov",
      "Eshmatov",
      "Eshankulov",
      "Ermanov",
      "Ergali",
      "Erdoğan",
      "Eraliev",
      "English",
      "Elshan",
      "Elizov",
      "Elias",
      "Elfrink",
      "El Mouden",
      "Efron",
      "Efe",
      "Edwards",
      "Edgard",
      "Eco",
      "Dusanov",
      "Durmanov",
      "Dre",
      "Dow",
      "Douaud",
      "Dostov",
      "Doroshenko",
      "Dora",
      "Doolan",
      "Doni",
      "Donaev",
      "Dona",
      "Don",
      "Domna",
      "Doktor",
      "Doğan",
      "Dobroskokov",
      "Djalolov",
      "Djabbarov",
      "Ditta",
      "Dincel",
      "Dimitri",
      "Dieste",
      "Dicks",
      "Diadora",
      "Di Matteo",
      "Dhali",
      "Dexkanov",
      "Devito",
      "Devise",
      "Devil",
      "Devers",
      "Denız",
      "Denisov",
      "Demon",
      "Demidov",
      "Demchenko",
      "Decoene",
      "Death",
      "De La Rosa",
      "Day",
      "Davila",
      "Dautov",
      "Darr",
      "Danko",
      "Damon",
      "Daliyev",
      "Daff",
      "Dabiri",
      "D'orville",
      "Cum",
      "Cruz",
      "Crùísê",
      "Crudup",
      "Coutinho",
      "Costa",
      "Cosmos",
      "Cooper",
      "Conville",
      "Conors",
      "Conerly",
      "Comellas",
      "Coll",
      "Cobain",
      "Cloud",
      "Clancy",
      "Cinema",
      "Chumley",
      "Chery",
      "Cherkashin",
      "Cherepanov",
      "Chef",
      "Charlin",
      "Charle",
      "Charif",
      "Chaplin",
      "Cena",
      "Catovic",
      "Cathcart",
      "Castillo",
      "Carstairs",
      "Carson",
      "Carey",
      "Care",
      "Caraballo",
      "Candy",
      "Camp",
      "Cambria",
      "Cam",
      "Calafell",
      "Cabrera",
      "Byrne",
      "Buzikov",
      "Buva",
      "Butaev",
      "Burxanov",
      "Buronov",
      "Burhonov",
      "Buran",
      "Bunny",
      "Bulut",
      "Bulen",
      "Bryant",
      "Bri",
      "Bozorboyev",
      "Bozkuş",
      "Boutique",
      "Bots",
      "Bossov",
      "Boss",
      "Bonno",
      "Bondarchuk",
      "Bolbas",
      "Bola",
      "Bodol",
      "Blancos",
      "Blache",
      "Birnbaum",
      "Binning",
      "Bilir",
      "Bilge",
      "Bierd",
      "Berdikulov",
      "Ber",
      "Bennet",
      "Belous",
      "Belmont",
      "Bell",
      "Belikov",
      "Bektaş",
      "Bekmuratov",
      "Bekmetov",
      "Behunin",
      "Beek",
      "Becman",
      "Beckovsky",
      "Bearn",
      "Bay",
      "Batt",
      "Bassi",
      "Başlı",
      "Bashiri",
      "Basha",
      "Bash",
      "Basak",
      "Barsa",
      "Barrio",
      "Barrera",
      "Baronin",
      "Barakat",
      "Bank",
      "Baloch",
      "Balbuena",
      "Balabekov",
      "Bakhtiyarov",
      "Bakhramov",
      "Bak",
      "Bagirov",
      "Baev",
      "Badritdinov",
      "Badr",
      "Baby",
      "Baburov",
      "Babikov",
      "Babakulov",
      "Babadjanov",
      "Baba",
      "Azizi",
      "Ayyari",
      "Ayubov",
      "Aytaş",
      "Aydin",
      "Axmadjanov",
      "Axanov",
      "Axadov",
      "Augusta",
      "Atwood",
      "Ataxanov",
      "Astrup",
      "Asthana",
      "Aslan",
      "Aslamov",
      "Asi",
      "Ashrapov",
      "Asamov",
      "Asal",
      "Arustamov",
      "Arslanov",
      "Arora",
      "Arif",
      "Arabian",
      "Antolin",
      "Angle",
      "An",
      "Amriev",
      "Amid",
      "Amerov",
      "Amanbaev",
      "Amaan",
      "Alwi",
      "Altuntaş",
      "Alsarhan",
      "Almatov",
      "Almat",
      "Allakhverdov",
      "Allabergenov",
      "Alizade",
      "Alinagi",
      "Alimatov",
      "Alimardanov",
      "Alikulov",
      "Alikhanov",
      "Aliani",
      "Alhassan",
      "Alexia",
      "Alena",
      "Alemdar",
      "Ald",
      "Albekov",
      "Al-Essa",
      "Akimov",
      "Akhmetov",
      "Akhmet",
      "Akhmad",
      "Aker",
      "Akdemir",
      "Akbarkhan",
      "Ahunov",
      "Ahun",
      "Ahrens",
      "Ahn",
      "Agrawal",
      "Aghati",
      "Agabekov",
      "Afkar",
      "Afandi",
      "Adriaen",
      "Adkins",
      "Aditya",
      "Adham",
      "Adem",
      "Adashev",
      "Acosta",
      "Abzalov",
      "Abubakirov",
      "Ablaev",
      "Abduvakhobov",
      "Abdusalamov",
      "Abduraupov",
      "Abdurahim",
      "Abdulmajid",
      "Abdulaziz",
      "Abdulayev",
      "Abdukayumov",
      "Abdujalilov",
      "Abdugafarov",
      "Abdikarimov",
      "Abdi",
      "Abbos"
    ]
  },
  "tier_probs": {
    "given": {
      "very_common": 0.55,
      "common": 0.3,
      "mid": 0.13,
      "rare": 0.02
    },
    "surname": {
      "very_common": 0.45,
      "common": 0.35,
      "mid": 0.17,
      "rare": 0.03
    }
  },
  "middle_name_prob": 0.15,
  "compound_surname_prob": 0.05,
  "surname_connector": "-",
  "pool_id": "country_UZB"
}
