{
  "pool_file": "C:/_Private/Misc/MotM/CursorGitClone/motm-backend/data/name_pools/country_ITA.json",
  "pool_id": "country_ITA",
  "country_code": "ITA",
  "before": {
    "tier_counts": {
      "very_common": 40,
      "common": 60,
      "mid": 100,
      "rare": 32317
    },
    "total": 32517
  },
  "after": {
    "tier_counts": {
      "very_common": 40,
      "common": 60,
      "mid": 100,
      "rare": 32181
    },
    "total": 32381
  },
  "removed": {
    "total": 136,
    "by_reason_counts": {
      "given_name_leak": 108,
      "global_overlap_outlier": 26,
      "placeholder": 2
    },
    "sample_by_reason": {
      "given_name_leak": [
        "Adam",
        "Alan",
        "Albert",
        "Alex",
        "Alexander",
        "Andrew",
        "Anthony",
        "Arthur",
        "Ben",
        "Benjamin",
        "Bernard",
        "Brian",
        "Bruce",
        "Carl",
        "Charles",
        "Chris",
        "Christian",
        "Christopher",
        "Colin",
        "Connor",
        "Craig",
        "Daniel",
        "David",
        "Dean",
        "Dennis",
        "Duncan",
        "Edward",
        "Eric",
        "Ethan",
        "Frank",
        "Gabriel",
        "George",
        "Gordon",
        "Graham",
        "Grant",
        "Guy",
        "Harry",
        "Henry",
        "Ian",
        "Isaac",
        "Ivan",
        "Jack",
        "Jacob",
        "James",
        "Jason",
        "Joe",
        "John",
        "Johnny",
        "Jordan",
        "Joseph"
      ],
      "global_overlap_outlier": [
        "Abner",
        "Andromeda",
        "Bazzi",
        "Benvenuto",
        "Cesario",
        "Chichi",
        "Cipher",
        "Dibenedetto",
        "Fata",
        "Fauzan",
        "Higashi",
        "Mancia",
        "Marasigan",
        "Mecca",
        "Monza",
        "Murari",
        "Pesa",
        "Rabbi",
        "Raihan",
        "Randi",
        "Sabella",
        "Sikder",
        "Sparta",
        "Viernes",
        "Villano",
        "Zaina"
      ],
      "placeholder": [
        "Test",
        "Unknown"
      ]
    }
  }
}
